[
  {
    "company": "DriveTime",
    "position": "Product  Management Intern (Summer 2024)",
    "location": "Tempe, AZ",
    "work_model": "On Site",
    "date_posted": "Aug 28",
    "apply_link": "https://jobright.ai/jobs/info/68b05e0d2d46f6396cae4b86?utm_campaign=1047&utm_source=git",
    "company_url": "https://www.drivetime.com",
    "found_date": "2025-08-28T16:42:33.903893"
  },
  {
    "company": "DriveTime",
    "position": "Product Management Intern (Summer 2025)",
    "location": "Tempe, AZ",
    "work_model": "On Site",
    "date_posted": "Aug 28",
    "apply_link": "https://jobright.ai/jobs/info/68b05c7a2d46f6396cae4842?utm_campaign=1047&utm_source=git",
    "company_url": "",
    "found_date": "2025-08-28T16:42:33.903916"
  },
  {
    "company": "OCBC",
    "position": "[Internship: Global Markets, Global Market Equities, Digital Platforms [Jan to Jun 2026]](https://jobright.ai/jobs/info/68b04cda13563e782a9f4b45?utm_campaign=1047&utm_source=git)",
    "location": "South Centre, PA",
    "work_model": "On Site",
    "date_posted": "Aug 28",
    "apply_link": "",
    "company_url": "http://www.ocbc.com",
    "found_date": "2025-08-28T16:42:33.903927"
  },
  {
    "company": "T-Mobile",
    "position": "Summer 2025 IT Solution and Design Intern",
    "location": "Overland Park, Kansas",
    "work_model": "On Site",
    "date_posted": "Aug 28",
    "apply_link": "https://jobright.ai/jobs/info/68b03d8313563e782a9f4314?utm_campaign=1047&utm_source=git",
    "company_url": "https://www.t-mobile.com",
    "found_date": "2025-08-28T16:42:33.903935"
  },
  {
    "company": "Copart",
    "position": "Technology Product Analyst Intern",
    "location": "Dallas, TX",
    "work_model": "Hybrid",
    "date_posted": "Aug 27",
    "apply_link": "https://jobright.ai/jobs/info/68afc6e5e723db6c9b7b34ac?utm_campaign=1047&utm_source=git",
    "company_url": "http://www.copart.com",
    "found_date": "2025-08-28T16:42:33.903943"
  },
  {
    "company": "Relay",
    "position": "Relay Pathways Intern - Product Management",
    "location": "Raleigh, NC",
    "work_model": "On Site",
    "date_posted": "Aug 27",
    "apply_link": "https://jobright.ai/jobs/info/68afc557e723db6c9b7b32fe?utm_campaign=1047&utm_source=git",
    "company_url": "https://relaypro.com",
    "found_date": "2025-08-28T16:42:33.903951"
  },
  {
    "company": "Red Aspen",
    "position": "Product Development Intern",
    "location": "Meridian, ID",
    "work_model": "On Site",
    "date_posted": "Aug 27",
    "apply_link": "https://jobright.ai/jobs/info/68afcf52b47fb001d688d7fd?utm_campaign=1047&utm_source=git",
    "company_url": "https://www.redaspenlove.com",
    "found_date": "2025-08-28T16:42:33.903958"
  },
  {
    "company": "Zebra Technologies",
    "position": "2026 Summer Internship (US) - Jr. Product Manager",
    "location": "Holtsville, NY",
    "work_model": "On Site",
    "date_posted": "Aug 27",
    "apply_link": "https://jobright.ai/jobs/info/68afa6001f0a2a568a062fcc?utm_campaign=1047&utm_source=git",
    "company_url": "https://www.zebra.com",
    "found_date": "2025-08-28T16:42:33.903967"
  },
  {
    "company": "Wonder",
    "position": "Ops Product Intern - Summer 2026",
    "location": "New York, NY",
    "work_model": "On Site",
    "date_posted": "Aug 27",
    "apply_link": "https://jobright.ai/jobs/info/68af99b4962903596357ddb5?utm_campaign=1047&utm_source=git",
    "company_url": "https://www.wonder.com",
    "found_date": "2025-08-28T16:42:33.903974"
  },
  {
    "company": "Mastercard",
    "position": "Product Management Intern, Summer 2026 - United States",
    "location": "Arlington, Virginia",
    "work_model": "On Site",
    "date_posted": "Aug 27",
    "apply_link": "https://jobright.ai/jobs/info/68af7eeb2daaba398441ecad?utm_campaign=1047&utm_source=git",
    "company_url": "http://www.mastercard.com",
    "found_date": "2025-08-28T16:42:33.903981"
  },
  {
    "company": "Mastercard",
    "position": "Product Management Intern, Summer 2026 - United States",
    "location": "O'Fallon, Missouri",
    "work_model": "On Site",
    "date_posted": "Aug 27",
    "apply_link": "https://jobright.ai/jobs/info/68af7ece2daaba398441ec8e?utm_campaign=1047&utm_source=git",
    "company_url": "",
    "found_date": "2025-08-28T16:42:33.903989"
  },
  {
    "company": "Mastercard",
    "position": "Product Management Intern, Summer 2026 - United States",
    "location": "Purchase, New York",
    "work_model": "On Site",
    "date_posted": "Aug 27",
    "apply_link": "https://jobright.ai/jobs/info/68af7e1f1f0a2a568a0622d1?utm_campaign=1047&utm_source=git",
    "company_url": "",
    "found_date": "2025-08-28T16:42:33.903995"
  },
  {
    "company": "Munich Re",
    "position": "Product Management Intern, NA Integrated Analytics (2026 Summer - New York)",
    "location": "NYC Metro Area",
    "work_model": "Hybrid",
    "date_posted": "Aug 27",
    "apply_link": "https://jobright.ai/jobs/info/68af6ae82daaba398441e066?utm_campaign=1047&utm_source=git",
    "company_url": "https://www.munichre.com",
    "found_date": "2025-08-28T16:42:33.904002"
  },
  {
    "company": "Wonder",
    "position": "Ops Product Intern - Summer 2026",
    "location": "New York, NY",
    "work_model": "Hybrid",
    "date_posted": "Aug 27",
    "apply_link": "https://jobright.ai/jobs/info/68af5f44962903596357c34d?utm_campaign=1047&utm_source=git",
    "company_url": "https://www.wonder.com",
    "found_date": "2025-08-28T16:42:33.904008"
  },
  {
    "company": "Hormel Foods",
    "position": "R&D Product Development Intern -Summer 2026- Austin, MN or Northbrook, IL",
    "location": "Austin, MN, United States",
    "work_model": "On Site",
    "date_posted": "Aug 27",
    "apply_link": "https://jobright.ai/jobs/info/68af54a82daaba398441d4c3?utm_campaign=1047&utm_source=git",
    "company_url": "http://www.hormelfoods.com/",
    "found_date": "2025-08-28T16:42:33.904014"
  },
  {
    "company": "Hormel Foods",
    "position": "R&D Product Development Intern -Summer 2026- Austin, MN or Northbrook, IL",
    "location": "1 Hormel Place, Austin, MN, 55912, US",
    "work_model": "On Site",
    "date_posted": "Aug 27",
    "apply_link": "https://jobright.ai/jobs/info/68af534b2daaba398441d345?utm_campaign=1047&utm_source=git",
    "company_url": "",
    "found_date": "2025-08-28T16:42:33.904021"
  },
  {
    "company": "Analog Devices",
    "position": "Product Applications Intern",
    "location": "Wilmington, MA",
    "work_model": "On Site",
    "date_posted": "Aug 26",
    "apply_link": "https://jobright.ai/jobs/info/68aea9cf7bcb7608b3d28c39?utm_campaign=1047&utm_source=git",
    "company_url": "http://www.analog.com",
    "found_date": "2025-08-28T16:42:33.904027"
  },
  {
    "company": "SharkNinja",
    "position": "Spring 2026: Product Development Co-op, Ninja (January through June)",
    "location": "Needham, MA",
    "work_model": "On Site",
    "date_posted": "Aug 26",
    "apply_link": "https://jobright.ai/jobs/info/68ae9b3903c5f15c2fd8a62e?utm_campaign=1047&utm_source=git",
    "company_url": "http://www.sharkninja.com",
    "found_date": "2025-08-28T16:42:33.904033"
  },
  {
    "company": "SharkNinja",
    "position": "Spring 2026: Product Development Co-op, CORE Quality (January through June)",
    "location": "Needham, MA",
    "work_model": "On Site",
    "date_posted": "Aug 26",
    "apply_link": "https://jobright.ai/jobs/info/68ae9aa42daaba3984418f46?utm_campaign=1047&utm_source=git",
    "company_url": "",
    "found_date": "2025-08-28T16:42:33.904039"
  },
  {
    "company": "SharkNinja",
    "position": "Spring 2026: Product Development Co-op, Shark (January through June)",
    "location": "Needham, MA",
    "work_model": "On Site",
    "date_posted": "Aug 26",
    "apply_link": "https://jobright.ai/jobs/info/68ae994903c5f15c2fd8a42d?utm_campaign=1047&utm_source=git",
    "company_url": "",
    "found_date": "2025-08-28T16:42:33.904045"
  },
  {
    "company": "Analog Devices",
    "position": "Product Applications Intern",
    "location": "US, MA, Wilmington",
    "work_model": "On Site",
    "date_posted": "Aug 26",
    "apply_link": "https://jobright.ai/jobs/info/68ae898ddaf1431824ca3cc3?utm_campaign=1047&utm_source=git",
    "company_url": "http://www.analog.com",
    "found_date": "2025-08-28T16:42:33.904051"
  },
  {
    "company": "Analog Devices",
    "position": "Product Applications Intern",
    "location": "US, CO, Colorado Springs, Centennial",
    "work_model": "On Site",
    "date_posted": "Aug 26",
    "apply_link": "https://jobright.ai/jobs/info/68ae894ed627244576e54c5d?utm_campaign=1047&utm_source=git",
    "company_url": "",
    "found_date": "2025-08-28T16:42:33.904057"
  },
  {
    "company": "Analog Devices",
    "position": "Product Applications Intern",
    "location": "US, NC, Durham",
    "work_model": "On Site",
    "date_posted": "Aug 26",
    "apply_link": "https://jobright.ai/jobs/info/68ae88eddaf1431824ca3c83?utm_campaign=1047&utm_source=git",
    "company_url": "",
    "found_date": "2025-08-28T16:42:33.904062"
  },
  {
    "company": "Altruist",
    "position": "Product Management Intern - Summer 2026",
    "location": "Los Angeles, CA",
    "work_model": "Hybrid",
    "date_posted": "Aug 26",
    "apply_link": "https://jobright.ai/jobs/info/689144544c7e851b90acd510?utm_campaign=1047&utm_source=git",
    "company_url": "https://altruist.com",
    "found_date": "2025-08-28T16:42:33.904068"
  },
  {
    "company": "Zebra Technologies",
    "position": "2026 Summer Internship (US) - Gen AI Product Management",
    "location": "Holtsville, NY",
    "work_model": "On Site",
    "date_posted": "Aug 26",
    "apply_link": "https://jobright.ai/jobs/info/68ae3e71758f2e4ac3012453?utm_campaign=1047&utm_source=git",
    "company_url": "https://www.zebra.com",
    "found_date": "2025-08-28T16:42:33.904075"
  },
  {
    "company": "Grange Insurance",
    "position": "Personal Lines Product Intern (hybrid)",
    "location": "Columbus, OH",
    "work_model": "Hybrid",
    "date_posted": "Aug 26",
    "apply_link": "https://jobright.ai/jobs/info/68ae016e758f2e4ac30101aa?utm_campaign=1047&utm_source=git",
    "company_url": "https://www.grangeinsurance.com/",
    "found_date": "2025-08-28T16:42:33.904082"
  },
  {
    "company": "Pentair",
    "position": "Product Management Leadership Development Internship Program - Summer 2026",
    "location": "Milwaukee, WI",
    "work_model": "On Site",
    "date_posted": "Aug 26",
    "apply_link": "https://jobright.ai/jobs/info/689173bcf5ee707a15dbe991?utm_campaign=1047&utm_source=git",
    "company_url": "http://www.pentair.com",
    "found_date": "2025-08-28T16:42:33.904088"
  },
  {
    "company": "SharkNinja",
    "position": "Spring 2026: Product Development Co-op, CORE Quality (January through June)",
    "location": "Needham, MA, United States",
    "work_model": "On Site",
    "date_posted": "Aug 26",
    "apply_link": "https://jobright.ai/jobs/info/68adc42cd627244576e4ec5f?utm_campaign=1047&utm_source=git",
    "company_url": "http://www.sharkninja.com",
    "found_date": "2025-08-28T16:42:33.904094"
  },
  {
    "company": "Altruist",
    "position": "Product Management Intern - Summer 2026",
    "location": "San Francisco, CA",
    "work_model": "Hybrid",
    "date_posted": "Aug 26",
    "apply_link": "https://jobright.ai/jobs/info/6891439c4c7e851b90acd4c6?utm_campaign=1047&utm_source=git",
    "company_url": "https://altruist.com",
    "found_date": "2025-08-28T16:42:33.904100"
  },
  {
    "company": "SharkNinja",
    "position": "Spring 2026: Product Development Co-op, Ninja (January through June)",
    "location": "Needham, MA, United States",
    "work_model": "On Site",
    "date_posted": "Aug 26",
    "apply_link": "https://jobright.ai/jobs/info/68adb094758f2e4ac300e0f0?utm_campaign=1047&utm_source=git",
    "company_url": "http://www.sharkninja.com",
    "found_date": "2025-08-28T16:42:33.904106"
  },
  {
    "company": "SharkNinja",
    "position": "Spring 2026: Product Development Co-op, Shark (January through June)",
    "location": "Needham, MA, United States",
    "work_model": "On Site",
    "date_posted": "Aug 26",
    "apply_link": "https://jobright.ai/jobs/info/68adb081daf1431824c9d7dc?utm_campaign=1047&utm_source=git",
    "company_url": "",
    "found_date": "2025-08-28T16:42:33.904112"
  },
  {
    "company": "Pentair",
    "position": "Product Management Leadership Development Internship Program - Summer 2026",
    "location": "Apex, NC",
    "work_model": "On Site",
    "date_posted": "Aug 26",
    "apply_link": "https://jobright.ai/jobs/info/689171aef5ee707a15dbe8e6?utm_campaign=1047&utm_source=git",
    "company_url": "http://www.pentair.com",
    "found_date": "2025-08-28T16:42:33.904119"
  },
  {
    "company": "Pentair",
    "position": "Product Management Leadership Development Internship Program - Summer 2026",
    "location": "Madison, WI",
    "work_model": "On Site",
    "date_posted": "Aug 26",
    "apply_link": "https://jobright.ai/jobs/info/689177d14c7e851b90acedf1?utm_campaign=1047&utm_source=git",
    "company_url": "",
    "found_date": "2025-08-28T16:42:33.904124"
  },
  {
    "company": "Pentair",
    "position": "Product Management Leadership Development Internship Program - Summer 2026",
    "location": "Charlotte, NC",
    "work_model": "On Site",
    "date_posted": "Aug 26",
    "apply_link": "https://jobright.ai/jobs/info/68916c18f47efe21139551b8?utm_campaign=1047&utm_source=git",
    "company_url": "",
    "found_date": "2025-08-28T16:42:33.904130"
  },
  {
    "company": "Pentair",
    "position": "Product Management Leadership Development Internship Program - Summer 2026",
    "location": "Golden Valley, MN",
    "work_model": "On Site",
    "date_posted": "Aug 26",
    "apply_link": "https://jobright.ai/jobs/info/689170aef47efe21139553b1?utm_campaign=1047&utm_source=git",
    "company_url": "",
    "found_date": "2025-08-28T16:42:33.904136"
  },
  {
    "company": "Pentair",
    "position": "Product Management Leadership Development Internship Program - Summer 2026",
    "location": "Chicago, IL",
    "work_model": "On Site",
    "date_posted": "Aug 26",
    "apply_link": "https://jobright.ai/jobs/info/689174c1f5ee707a15dbea11?utm_campaign=1047&utm_source=git",
    "company_url": "",
    "found_date": "2025-08-28T16:42:33.904142"
  },
  {
    "company": "Pentair",
    "position": "Product Management Leadership Development Internship Program - Summer 2026",
    "location": "Minneapolis, MN",
    "work_model": "On Site",
    "date_posted": "Aug 26",
    "apply_link": "https://jobright.ai/jobs/info/689175e6f47efe2113955864?utm_campaign=1047&utm_source=git",
    "company_url": "",
    "found_date": "2025-08-28T16:42:33.904148"
  },
  {
    "company": "Zebra Technologies",
    "position": "2026 Summer Internship (US) - Product Manager, Machine Vision",
    "location": "Holtsville, NY",
    "work_model": "On Site",
    "date_posted": "Aug 25",
    "apply_link": "https://jobright.ai/jobs/info/68ad6c36d627244576e4db8d?utm_campaign=1047&utm_source=git",
    "company_url": "https://www.zebra.com",
    "found_date": "2025-08-28T16:42:33.904155"
  },
  {
    "company": "Life Alive Caf\u00e9",
    "position": "Innovation and Product Development Intern",
    "location": "Cambridge, MA",
    "work_model": "On Site",
    "date_posted": "Aug 25",
    "apply_link": "https://jobright.ai/jobs/info/68ad317e758f2e4ac300b9f7?utm_campaign=1047&utm_source=git",
    "company_url": "http://www.lifealive.com",
    "found_date": "2025-08-28T16:42:33.904163"
  },
  {
    "company": "TikTok",
    "position": "Product Operations Project Intern - SMB Industry Operations - 2025 Start (BS/ MS)",
    "location": "Seattle, WA",
    "work_model": "On Site",
    "date_posted": "Aug 25",
    "apply_link": "https://jobright.ai/jobs/info/68ae1056d627244576e513ee?utm_campaign=1047&utm_source=git",
    "company_url": "https://www.tiktok.com",
    "found_date": "2025-08-28T16:42:33.904169"
  },
  {
    "company": "Tru Fragrance & Beauty",
    "position": "Intern, Product Development",
    "location": "New York, NY",
    "work_model": "Hybrid",
    "date_posted": "Aug 25",
    "apply_link": "https://jobright.ai/jobs/info/68acc2b0758f2e4ac30088cc?utm_campaign=1047&utm_source=git",
    "company_url": "https://www.trufragrance.com",
    "found_date": "2025-08-28T16:42:33.904176"
  },
  {
    "company": "Vertiv",
    "position": "Product Management/Engineering Internship (Summer 2026)",
    "location": "Delaware, OH",
    "work_model": "On Site",
    "date_posted": "Aug 25",
    "apply_link": "https://jobright.ai/jobs/info/68aca838758f2e4ac300772f?utm_campaign=1047&utm_source=git",
    "company_url": "https://www.Vertiv.com",
    "found_date": "2025-08-28T16:42:33.904182"
  },
  {
    "company": "E.L.F. BEAUTY",
    "position": "Intern, Product Development",
    "location": "Oakland, CA",
    "work_model": "Hybrid",
    "date_posted": "Aug 25",
    "apply_link": "https://jobright.ai/jobs/info/68aca754758f2e4ac3007668?utm_campaign=1047&utm_source=git",
    "company_url": "https://www.elfbeauty.com",
    "found_date": "2025-08-28T16:42:33.904188"
  },
  {
    "company": "Vertiv",
    "position": "Product Management Internship (Summer 2026)",
    "location": "Delaware, OH",
    "work_model": "On Site",
    "date_posted": "Aug 25",
    "apply_link": "https://jobright.ai/jobs/info/68aca463d627244576e478c6?utm_campaign=1047&utm_source=git",
    "company_url": "https://www.Vertiv.com",
    "found_date": "2025-08-28T16:42:33.904194"
  },
  {
    "company": "Vertiv",
    "position": "Product Management Engineering MBA Internship (Summer 2026)",
    "location": "Delaware, OH",
    "work_model": "On Site",
    "date_posted": "Aug 25",
    "apply_link": "https://jobright.ai/jobs/info/68ac9afad627244576e473c3?utm_campaign=1047&utm_source=git",
    "company_url": "",
    "found_date": "2025-08-28T16:42:33.904201"
  },
  {
    "company": "Vertiv",
    "position": "Product Management MBA Internship (Summer 2026)",
    "location": "Delaware, OH",
    "work_model": "On Site",
    "date_posted": "Aug 25",
    "apply_link": "https://jobright.ai/jobs/info/68ac9a3f758f2e4ac3006d42?utm_campaign=1047&utm_source=git",
    "company_url": "",
    "found_date": "2025-08-28T16:42:33.904207"
  },
  {
    "company": "Vertiv",
    "position": "Product Management Internship (Summer 2026)",
    "location": "Delaware, OH, United States",
    "work_model": "On Site",
    "date_posted": "Aug 25",
    "apply_link": "https://jobright.ai/jobs/info/68ac9637daf1431824c963ff?utm_campaign=1047&utm_source=git",
    "company_url": "",
    "found_date": "2025-08-28T16:42:33.904213"
  },
  {
    "company": "Vertiv",
    "position": "Product Management Engineering MBA Internship (Summer 2026)",
    "location": "Delaware, OH, United States",
    "work_model": "On Site",
    "date_posted": "Aug 25",
    "apply_link": "https://jobright.ai/jobs/info/68ac9633d627244576e47011?utm_campaign=1047&utm_source=git",
    "company_url": "",
    "found_date": "2025-08-28T16:42:33.904219"
  },
  {
    "company": "Vertiv",
    "position": "Product Management MBA Internship (Summer 2026)",
    "location": "Delaware, OH, United States",
    "work_model": "On Site",
    "date_posted": "Aug 25",
    "apply_link": "https://jobright.ai/jobs/info/68ac956bd627244576e46fe3?utm_campaign=1047&utm_source=git",
    "company_url": "",
    "found_date": "2025-08-28T16:42:33.904225"
  },
  {
    "company": "A Igreja de Jesus Cristo dos Santos dos \u00daltimos Dias",
    "position": "2026 Product Manager Technical paid intern (Jan and May hires)",
    "location": "Riverton, UT",
    "work_model": "Hybrid",
    "date_posted": "Aug 25",
    "apply_link": "https://jobright.ai/jobs/info/68ac8896758f2e4ac30064e8?utm_campaign=1047&utm_source=git",
    "company_url": "https://www.churchofjesuschrist.org/?lang=por",
    "found_date": "2025-08-28T16:42:33.904232"
  },
  {
    "company": "Vertiv",
    "position": "Product Management/Engineering Internship (Summer 2026)",
    "location": "United States",
    "work_model": "Remote",
    "date_posted": "Aug 25",
    "apply_link": "https://jobright.ai/jobs/info/68ac79be758f2e4ac3005e17?utm_campaign=1047&utm_source=git",
    "company_url": "https://www.Vertiv.com",
    "found_date": "2025-08-28T16:42:33.904239"
  },
  {
    "company": "Prudential Financial",
    "position": "Prudential: 2026 Global Technology & Operations, Internship Program",
    "location": "Newark, NJ",
    "work_model": "Hybrid",
    "date_posted": "Aug 25",
    "apply_link": "https://jobright.ai/jobs/info/68ac773ad627244576e460a7?utm_campaign=1047&utm_source=git",
    "company_url": "http://www.prudential.com",
    "found_date": "2025-08-28T16:42:33.904245"
  },
  {
    "company": "The Church of Jesus Christ of Latter-day Saints",
    "position": "2026 Product Manager Technical paid intern (Jan and May hires)",
    "location": "Riverton, UT",
    "work_model": "Hybrid",
    "date_posted": "Aug 25",
    "apply_link": "https://jobright.ai/jobs/info/68ac76dcd627244576e4604a?utm_campaign=1047&utm_source=git",
    "company_url": "https://www.lds.org",
    "found_date": "2025-08-28T16:42:33.904251"
  },
  {
    "company": "E.L.F. BEAUTY",
    "position": "Intern, Product Development",
    "location": "Oakland, CA",
    "work_model": "Hybrid",
    "date_posted": "Aug 25",
    "apply_link": "https://jobright.ai/jobs/info/68ac7688758f2e4ac3005c5d?utm_campaign=1047&utm_source=git",
    "company_url": "https://www.elfbeauty.com",
    "found_date": "2025-08-28T16:42:33.904258"
  },
  {
    "company": "PGIM",
    "position": "Prudential: 2026 Global Technology & Operations, Internship Program",
    "location": "Newark, NJ, USA",
    "work_model": "Hybrid",
    "date_posted": "Aug 25",
    "apply_link": "https://jobright.ai/jobs/info/68ac75e6758f2e4ac3005b55?utm_campaign=1047&utm_source=git",
    "company_url": "https://www.pgim.com",
    "found_date": "2025-08-28T16:42:33.904264"
  },
  {
    "company": "griddable.io",
    "position": "Summer 2026 Intern - Product Growth",
    "location": "San Francisco, CA",
    "work_model": "On Site",
    "date_posted": "Aug 25",
    "apply_link": "https://jobright.ai/jobs/info/68b04a8113563e782a9f47a0?utm_campaign=1047&utm_source=git",
    "company_url": "https://griddable.io",
    "found_date": "2025-08-28T16:42:33.904270"
  },
  {
    "company": "The Church of Jesus Christ of Latter-day Saints",
    "position": "2026 Product Manager Technical paid intern  (Jan and May hires)",
    "location": "Riverton, UT, United States",
    "work_model": "Hybrid",
    "date_posted": "Aug 25",
    "apply_link": "https://jobright.ai/jobs/info/68ac2116758f2e4ac3004574?utm_campaign=1047&utm_source=git",
    "company_url": "https://www.lds.org",
    "found_date": "2025-08-28T16:42:33.904277"
  },
  {
    "company": "FECON",
    "position": "Product Management Engineering Co-Op",
    "location": "Lebanon, OH",
    "work_model": "On Site",
    "date_posted": "Aug 24",
    "apply_link": "https://jobright.ai/jobs/info/68acc762d627244576e4901b?utm_campaign=1047&utm_source=git",
    "company_url": "http://fecon.com",
    "found_date": "2025-08-28T16:42:33.904283"
  },
  {
    "company": "Hunter Engineering Company",
    "position": "Product Management Intern",
    "location": "Bridgeton, MO",
    "work_model": "On Site",
    "date_posted": "Aug 22",
    "apply_link": "https://jobright.ai/jobs/info/68a8d2a7758f2e4ac3ff5a54?utm_campaign=1047&utm_source=git",
    "company_url": "http://www.hunter.com",
    "found_date": "2025-08-28T16:42:33.904289"
  },
  {
    "company": "HARMAN International",
    "position": "Product Management Intern",
    "location": "Los Angeles, CA",
    "work_model": "Hybrid",
    "date_posted": "Aug 22",
    "apply_link": "https://jobright.ai/jobs/info/68a874ff6acf96396f72016a?utm_campaign=1047&utm_source=git",
    "company_url": "https://www.harman.com/",
    "found_date": "2025-08-28T16:42:33.904295"
  },
  {
    "company": "HARMAN International",
    "position": "Product Management Intern",
    "location": "Northridge - California, USA",
    "work_model": "Hybrid",
    "date_posted": "Aug 22",
    "apply_link": "https://jobright.ai/jobs/info/68a81dc1d627244576e3174a?utm_campaign=1047&utm_source=git",
    "company_url": "",
    "found_date": "2025-08-28T16:42:33.904301"
  },
  {
    "company": "TikTok",
    "position": "Product Manager Intern (TikTok-Product-Social and Creation)- 2025 Summer (BS/MS)",
    "location": "San Jose, CA",
    "work_model": "On Site",
    "date_posted": "Aug 21",
    "apply_link": "https://jobright.ai/jobs/info/68aea3052daaba39844192f9?utm_campaign=1047&utm_source=git",
    "company_url": "https://www.tiktok.com",
    "found_date": "2025-08-28T16:42:33.904307"
  },
  {
    "company": "TikTok",
    "position": "Product Manager Intern (TikTok LIVE-Ecosystem Governance)- 2025 Summer (MBA)",
    "location": "San Jose, CA",
    "work_model": "On Site",
    "date_posted": "Aug 21",
    "apply_link": "https://jobright.ai/jobs/info/68a9520ad627244576e38e3a?utm_campaign=1047&utm_source=git",
    "company_url": "",
    "found_date": "2025-08-28T16:42:33.904314"
  },
  {
    "company": "TikTok",
    "position": "Product Manager Intern (TikTok LIVE-Ecosystem Governance) - 2025 Summer (BS/MS)",
    "location": "San Jose, CA",
    "work_model": "On Site",
    "date_posted": "Aug 21",
    "apply_link": "https://jobright.ai/jobs/info/68ae8fc5daf1431824ca41b1?utm_campaign=1047&utm_source=git",
    "company_url": "",
    "found_date": "2025-08-28T16:42:33.904319"
  },
  {
    "company": "TikTok",
    "position": "[Product Manager Intern [TikTok-Product-Search Growth]- 2026 Summer (BS/MS)](https://jobright.ai/jobs/info/6891886c4c7e851b90acf90e?utm_campaign=1047&utm_source=git)",
    "location": "San Jose, CA",
    "work_model": "On Site",
    "date_posted": "Aug 21",
    "apply_link": "",
    "company_url": "",
    "found_date": "2025-08-28T16:42:33.904326"
  },
  {
    "company": "TikTok",
    "position": "Product Solutions and Operations Project Intern - Content and Service Ads- Fall 2025 (BS/ MS)",
    "location": "New York, United States",
    "work_model": "On Site",
    "date_posted": "Aug 21",
    "apply_link": "https://jobright.ai/jobs/info/68a7ca30d627244576e2ed8d?utm_campaign=1047&utm_source=git",
    "company_url": "",
    "found_date": "2025-08-28T16:42:33.904348"
  },
  {
    "company": "Juniper Systems",
    "position": "Product Management Intern",
    "location": "Logan, UT",
    "work_model": "On Site",
    "date_posted": "Aug 21",
    "apply_link": "https://jobright.ai/jobs/info/68a915fe758f2e4ac3ff7387?utm_campaign=1047&utm_source=git",
    "company_url": "http://junipersys.com",
    "found_date": "2025-08-28T16:42:33.904356"
  },
  {
    "company": "TikTok",
    "position": "Product Manager Intern (Content and Service Lead Ads ) - 2026 Summer (BS/MS)",
    "location": "San Jose, CA",
    "work_model": "On Site",
    "date_posted": "Aug 21",
    "apply_link": "https://jobright.ai/jobs/info/689c3a5d79a9f96662537dd0?utm_campaign=1047&utm_source=git",
    "company_url": "https://www.tiktok.com",
    "found_date": "2025-08-28T16:42:33.904362"
  },
  {
    "company": "TikTok",
    "position": "Product Manager Intern (TikTok-PGC)- 2026 Summer (BS/MS)",
    "location": "San Jose, CA",
    "work_model": "On Site",
    "date_posted": "Aug 21",
    "apply_link": "https://jobright.ai/jobs/info/689d3c9679a9f9666253e8f0?utm_campaign=1047&utm_source=git",
    "company_url": "",
    "found_date": "2025-08-28T16:42:33.904369"
  },
  {
    "company": "Upstart",
    "position": "Join our Product Talent Community!",
    "location": "United States",
    "work_model": "Remote",
    "date_posted": "Aug 21",
    "apply_link": "https://jobright.ai/jobs/info/68a7a6cd33dd7158bbca894f?utm_campaign=1047&utm_source=git",
    "company_url": "https://upstart.com/about",
    "found_date": "2025-08-28T16:42:33.904374"
  },
  {
    "company": "TikTok",
    "position": "[Product Manager Intern [TikTok LIVE-Ecosystem Governance]-2026 Summer (BS/MS)](https://jobright.ai/jobs/info/689a9d2a5574fd6bc0c8416f?utm_campaign=1047&utm_source=git)",
    "location": "San Jose, CA",
    "work_model": "On Site",
    "date_posted": "Aug 21",
    "apply_link": "",
    "company_url": "https://www.tiktok.com",
    "found_date": "2025-08-28T16:42:33.904381"
  }
]